cs307pl/__init__.py
cs307pl-0.1.0.dist-info/METADATA
cs307pl-0.1.0.dist-info/WHEEL
cs307pl-0.1.0.dist-info/entry_points.txt
cs307pl-0.1.0.dist-info/RECORD
