Metadata-Version: 2.3
Name: cs307pl
Version: 0.1.0
Summary: Python package for CS 307 PrairieLearn usage
Author-email: David Dalpiaz <dalpiaz2@illinois.edu>
Requires-Python: >=3.12
Requires-Dist: np>=1.0.2
Requires-Dist: pandas>=2.2.3
